anysite/__init__.py
anysite/__main__.py
anysite/main.py
anysite/py.typed
anysite/api/__init__.py
anysite/api/client.py
anysite/api/errors.py
anysite/api/schemas.py
anysite/batch/__init__.py
anysite/batch/executor.py
anysite/batch/input.py
anysite/batch/rate_limiter.py
anysite/cli/__init__.py
anysite/cli/config.py
anysite/cli/executor.py
anysite/cli/options.py
anysite/config/__init__.py
anysite/config/paths.py
anysite/config/settings.py
anysite/dataset/__init__.py
anysite/dataset/analyzer.py
anysite/dataset/cli.py
anysite/dataset/collector.py
anysite/dataset/db_loader.py
anysite/dataset/errors.py
anysite/dataset/exporters.py
anysite/dataset/history.py
anysite/dataset/models.py
anysite/dataset/notifications.py
anysite/dataset/scheduler.py
anysite/dataset/storage.py
anysite/dataset/transformer.py
anysite/db/__init__.py
anysite/db/cli.py
anysite/db/config.py
anysite/db/manager.py
anysite/db/adapters/__init__.py
anysite/db/adapters/base.py
anysite/db/adapters/postgres.py
anysite/db/adapters/sqlite.py
anysite/db/operations/__init__.py
anysite/db/operations/insert.py
anysite/db/operations/query.py
anysite/db/schema/__init__.py
anysite/db/schema/inference.py
anysite/db/schema/types.py
anysite/db/utils/__init__.py
anysite/db/utils/sanitize.py
anysite/models/__init__.py
anysite/output/__init__.py
anysite/output/console.py
anysite/output/formatters.py
anysite/output/templates.py
anysite/streaming/__init__.py
anysite/streaming/progress.py
anysite/streaming/writer.py
anysite/utils/__init__.py
anysite/utils/fields.py
anysite/utils/retry.py
anysite_cli-0.1.2.dist-info/METADATA
anysite_cli-0.1.2.dist-info/WHEEL
anysite_cli-0.1.2.dist-info/entry_points.txt
anysite_cli-0.1.2.dist-info/licenses/LICENSE
anysite_cli-0.1.2.dist-info/RECORD
