Metadata-Version: 2.4
Name: anysite-cli
Version: 0.1.2
Summary: CLI for Anysite API - web data extraction for humans and AI agents
Project-URL: Homepage, https://anysite.io
Project-URL: Documentation, https://docs.anysite.io/cli
Project-URL: Repository, https://github.com/anysiteio/anysite-cli
Project-URL: Issues, https://github.com/anysiteio/anysite-cli/issues
Author-email: Anysite Team <support@anysite.io>
License-Expression: MIT
License-File: LICENSE
Keywords: api,cli,instagram,linkedin,scraping,twitter
Classifier: Development Status :: 4 - Beta
Classifier: Environment :: Console
Classifier: Intended Audience :: Developers
Classifier: License :: OSI Approved :: MIT License
Classifier: Operating System :: OS Independent
Classifier: Programming Language :: Python :: 3
Classifier: Programming Language :: Python :: 3.11
Classifier: Programming Language :: Python :: 3.12
Classifier: Programming Language :: Python :: 3.13
Classifier: Programming Language :: Python :: 3.14
Classifier: Topic :: Internet :: WWW/HTTP
Classifier: Topic :: Software Development :: Libraries
Classifier: Topic :: Utilities
Requires-Python: >=3.11
Requires-Dist: httpx>=0.25.0
Requires-Dist: orjson>=3.9.0
Requires-Dist: pydantic-settings>=2.0.0
Requires-Dist: pydantic>=2.0.0
Requires-Dist: python-dotenv>=1.0.0
Requires-Dist: pyyaml>=6.0.0
Requires-Dist: rich>=13.0.0
Requires-Dist: tabulate>=0.9.0
Requires-Dist: typer[all]>=0.9.0
Provides-Extra: all
Requires-Dist: duckdb>=1.0.0; extra == 'all'
Requires-Dist: httpx>=0.25.0; extra == 'all'
Requires-Dist: psycopg[binary]>=3.1.0; extra == 'all'
Requires-Dist: pyarrow>=15.0.0; extra == 'all'
Requires-Dist: pymysql>=1.1.0; extra == 'all'
Provides-Extra: data
Requires-Dist: duckdb>=1.0.0; extra == 'data'
Requires-Dist: httpx>=0.25.0; extra == 'data'
Requires-Dist: pyarrow>=15.0.0; extra == 'data'
Provides-Extra: db
Requires-Dist: psycopg[binary]>=3.1.0; extra == 'db'
Requires-Dist: pymysql>=1.1.0; extra == 'db'
Provides-Extra: dev
Requires-Dist: mypy>=1.5.0; extra == 'dev'
Requires-Dist: pytest-asyncio>=0.21.0; extra == 'dev'
Requires-Dist: pytest-cov>=4.1.0; extra == 'dev'
Requires-Dist: pytest>=7.4.0; extra == 'dev'
Requires-Dist: respx>=0.20.0; extra == 'dev'
Requires-Dist: ruff>=0.1.0; extra == 'dev'
Requires-Dist: types-pyyaml>=6.0.0; extra == 'dev'
Requires-Dist: types-tabulate>=0.9.0; extra == 'dev'
Provides-Extra: mysql
Requires-Dist: pymysql>=1.1.0; extra == 'mysql'
Provides-Extra: postgres
Requires-Dist: psycopg[binary]>=3.1.0; extra == 'postgres'
